scriptcwl/__init__.py
scriptcwl/library.py
scriptcwl/reference.py
scriptcwl/scriptcwl.py
scriptcwl/step.py
scriptcwl/workflow.py
scriptcwl/yamlutils.py
scriptcwl/examples/__init__.py
scriptcwl/examples/add.cwl
scriptcwl/examples/add.py
scriptcwl/examples/add_multiply_example.cwl
scriptcwl/examples/multiply.cwl
scriptcwl/examples/multiply.py
scriptcwl-0.8.0.dist-info/LICENSE
scriptcwl-0.8.0.dist-info/METADATA
scriptcwl-0.8.0.dist-info/WHEEL
scriptcwl-0.8.0.dist-info/top_level.txt
scriptcwl-0.8.0.dist-info/RECORD
