Metadata-Version: 2.1
Name: scriptcwl
Version: 0.8.0
Summary: Tool to generate CWL workflows
Home-page: https://github.com/nlesc/scriptcwl
Author: Janneke van der Zwaan
Author-email: j.vanderzwaan@esciencecenter.nl
License: Apache 2.0
Download-URL: https://github.com/NLeSC/scriptcwl/archive/0.8.0.tar.gz
Keywords: cwl,workflow,pipeline,common workflow language
Platform: UNKNOWN
Classifier: Development Status :: 3 - Alpha
Classifier: Intended Audience :: Developers
Classifier: License :: OSI Approved :: Apache Software License
Classifier: Programming Language :: Python :: 2
Classifier: Programming Language :: Python :: 2.7
Classifier: Programming Language :: Python :: 3
Classifier: Programming Language :: Python :: 3.4
Classifier: Programming Language :: Python :: 3.5
Classifier: Programming Language :: Python :: 3.6
Requires-Dist: six
Requires-Dist: cwltool (>=1.0.20170727112954)
Requires-Dist: click
